vagranttoansible/__init__.py
vagranttoansible/vagranttoansible.py
vagranttoansible-1.0.2.dist-info/DESCRIPTION.rst
vagranttoansible-1.0.2.dist-info/METADATA
vagranttoansible-1.0.2.dist-info/RECORD
vagranttoansible-1.0.2.dist-info/WHEEL
vagranttoansible-1.0.2.dist-info/entry_points.txt
vagranttoansible-1.0.2.dist-info/metadata.json
vagranttoansible-1.0.2.dist-info/top_level.txt
