Metadata-Version: 2.0
Name: vagranttoansible
Version: 1.0.2
Summary: Simple script to transform 'vagrant ssh-config' output to an inventory hosts for Ansible
Home-page: https://github.com/haidaraM/vagranttoansibleinventory
Author: HAIDARA Mohamed El Mouctar
Author-email: elmhaidara@gmail.com
License: MIT
Download-URL: https://github.com/haidaraM/vagranttoansibleinventory/archive/v1.0.2.tar.gz
Platform: UNKNOWN
Classifier: Development Status :: 4 - Beta
Classifier: Intended Audience :: Developers
Classifier: License :: OSI Approved :: MIT License
Classifier: Programming Language :: Python :: 3.5
Classifier: Programming Language :: Python :: 2.7
Requires-Dist: stormssh (==0.6.9)
